MANIFEST.in
README.md
requirements.txt
setup.cfg
setup.py
chainer_cyclegan/__init__.py
chainer_cyclegan.egg-info/PKG-INFO
chainer_cyclegan.egg-info/SOURCES.txt
chainer_cyclegan.egg-info/dependency_links.txt
chainer_cyclegan.egg-info/requires.txt
chainer_cyclegan.egg-info/top_level.txt
chainer_cyclegan/datasets/__init__.py
chainer_cyclegan/datasets/base.py
chainer_cyclegan/datasets/berkeley_cyclegan.py
chainer_cyclegan/datasets/berkeley_pix2pix.py
chainer_cyclegan/datasets/celeba.py
chainer_cyclegan/datasets/paired.py
chainer_cyclegan/extensions/__init__.py
chainer_cyclegan/extensions/cyclegan_evaluator.py
chainer_cyclegan/links/__init__.py
chainer_cyclegan/links/normalization/__init__.py
chainer_cyclegan/links/normalization/instance_normalization.py
chainer_cyclegan/models/__init__.py
chainer_cyclegan/models/discriminators.py
chainer_cyclegan/models/generators.py
chainer_cyclegan/updaters/__init__.py
chainer_cyclegan/updaters/cyclegan_updater.py