Metadata-Version: 1.0
Name: chainer-cyclegan
Version: 1.2.3
Summary: Chainer Implementation of CycleGAN.
Home-page: https://github.com/wkentaro/chainer-cyclegan
Author: Kentaro Wada
Author-email: www.kentaro.wada@gmail.com
License: MIT
Platform: UNKNOWN
